quark/__init__.py
quark/__main__.py
quark/cache.py
quark/config.py
quark/db.py
quark/deps.py
quark/install.py
quark/loader.py
quark/middleware.py
quark/quark.py
quark/schemas.py
quark/storage.py
quark/utils.py
quark/app/account.py
quark/app/action_log.py
quark/app/config.py
quark/app/dashboard.py
quark/app/department.py
quark/app/file.py
quark/app/image.py
quark/app/layout.py
quark/app/login.py
quark/app/menu.py
quark/app/permission.py
quark/app/position.py
quark/app/role.py
quark/app/upload.py
quark/app/user.py
quark/app/web_config.py
quark/app/actions/__init__.py
quark/app/actions/batch_delete.py
quark/app/actions/batch_delete_role.py
quark/app/actions/batch_disable.py
quark/app/actions/batch_enable.py
quark/app/actions/batch_export.py
quark/app/actions/change_status.py
quark/app/actions/create_drawer.py
quark/app/actions/create_link.py
quark/app/actions/create_modal.py
quark/app/actions/data_scope.py
quark/app/actions/delete.py
quark/app/actions/delete_role.py
quark/app/actions/delete_special.py
quark/app/actions/detail_drawer.py
quark/app/actions/detail_link.py
quark/app/actions/detail_modal.py
quark/app/actions/edit_drawer.py
quark/app/actions/edit_link.py
quark/app/actions/edit_modal.py
quark/app/actions/export.py
quark/app/actions/form_back.py
quark/app/actions/form_extra_back.py
quark/app/actions/form_reset.py
quark/app/actions/form_step.py
quark/app/actions/form_submit.py
quark/app/actions/import_action.py
quark/app/actions/menu_create_drawer.py
quark/app/actions/menu_edit_drawer.py
quark/app/actions/modal_form.py
quark/app/actions/more.py
quark/app/actions/select_options.py
quark/app/actions/status.py
quark/app/actions/sync_permission.py
quark/app/metrics/system_info.py
quark/app/metrics/team_info.py
quark/app/metrics/total_admin.py
quark/app/metrics/total_file.py
quark/app/metrics/total_image.py
quark/app/metrics/total_log.py
quark/app/searches/__init__.py
quark/app/searches/datetime_range.py
quark/app/searches/input.py
quark/app/searches/status.py
quark_py-0.1.4.dist-info/licenses/LICENSE
quark_py-0.1.4.dist-info/METADATA
quark_py-0.1.4.dist-info/WHEEL
quark_py-0.1.4.dist-info/top_level.txt
quark_py-0.1.4.dist-info/RECORD
