Metadata-Version: 2.4
Name: quark-py
Version: 0.1.4
Summary: FastAPI + Ant Design Pro front-end and back-end separated admin dashboard, Build Anything With Quark
Requires-Python: <3.13,>=3.10
License-File: LICENSE
Requires-Dist: aiomysql>=0.2.0
Requires-Dist: bcrypt>=4.3.0
Requires-Dist: captcha>=0.7.1
Requires-Dist: fastapi>=0.115.12
Requires-Dist: fastapi-cache2>=0.2.2
Requires-Dist: python-multipart>=0.0.5
Requires-Dist: openpyxl>=3.1.5
Requires-Dist: pandas>=2.3.1
Requires-Dist: psutil>=7.0.0
Requires-Dist: inflection>=0.5.1
Requires-Dist: python-i18n>=0.3.9
Requires-Dist: python-jose[cryptography]>=3.5.0
Requires-Dist: tortoise-orm>=0.25.0
Requires-Dist: uvicorn>=0.34.2
Requires-Dist: filetype>=1.2.0
Dynamic: license-file
